Workbook

Sheet VALOR NOMINAL - TODOS OS TRAB
E1: VALOR NOMINAL - TODOS OS TRABALHOS
A2: UF | B2: DESCRIÇÃO | C2: CNAE | D2: DESCRIÇÃO | E2: POP. OCUPADA | F2: MASSA DE RENDIMENTOS
A3: 11 | B3: =VLOOKUP(VALUE(A3), 'DICIONÁRIO UF'!$A:$B, 2, FALSE) -> Rondônia | C3: 0 | D3: =VLOOKUP(C3, 'DICIONÁRIO CNAES'!$A:$B, 2, FALSE) -> Atividades mal definidas | E3: 1457.3456 | F3: 1395917
A4: 11 | B4: =VLOOKUP(VALUE(A4), 'DICIONÁRIO UF'!$A:$B, 2, FALSE) -> Rondônia | C4: 1101 | D4: =VLOOKUP(C4, 'DICIONÁRIO CNAES'!$A:$B, 2, FALSE) -> Cultivo de arroz | E4: 340.24151 | F4: 563043.82
A5: 11 | B5: =VLOOKUP(VALUE(A5), 'DICIONÁRIO UF'!$A:$B, 2, FALSE) -> Rondônia | C5: 1102 | D5: =VLOOKUP(C5, 'DICIONÁRIO CNAES'!$A:$B, 2, FALSE) -> Cultivo de milho | E5: 701.56982 | F5: 902293.85
A6: 11 | B6: =VLOOKUP(VALUE(A6), 'DICIONÁRIO UF'!$A:$B, 2, FALSE) -> Rondônia | C6: 1105 | D6: =VLOOKUP(C6, 'DICIONÁRIO CNAES'!$A:$B, 2, FALSE) -> Cultivo de cana-de-açúcar | E6: 315.78708 | F6: 126314.83
A7: 11 | B7: =VLOOKUP(VALUE(A7), 'DICIONÁRIO UF'!$A:$B, 2, FALSE) -> Rondônia | C7: 1107 | D7: =VLOOKUP(C7, 'DICIONÁRIO CNAES'!$A:$B, 2, FALSE) -> Cultivo de soja | E7: 5764.1758 | F7: 15306268 | I7: =IFERROR(VLOOKUP(A3, 'DICIONÁRIO UF'!A:B, 2, FALSE), "")
A8: 11 | B8: =VLOOKUP(VALUE(A8), 'DICIONÁRIO UF'!$A:$B, 2, FALSE) -> Rondônia | C8: 1108 | D8: =VLOOKUP(C8, 'DICIONÁRIO CNAES'!$A:$B, 2, FALSE) -> Cultivo de mandioca | E8: 4053.7574 | F8: 3675132.4
A9: 11 | B9: =VLOOKUP(VALUE(A9), 'DICIONÁRIO UF'!$A:$B, 2, FALSE) -> Rondônia | C9: 1109 | D9: =VLOOKUP(C9, 'DICIONÁRIO CNAES'!$A:$B, 2, FALSE) -> Cultivo de outras lavouras temporárias não especificadas anteriormente | E9: 3188.6404 | F9: 2291344.2
A10: 11 | B10: =VLOOKUP(VALUE(A10), 'DICIONÁRIO UF'!$A:$B, 2, FALSE) -> Rondônia | C10: 1110 | D10: =VLOOKUP(C10, 'DICIONÁRIO CNAES'!$A:$B, 2, FALSE) -> Horticultura | E10: 3724.9521 | F10: 3816529.4
A11: 11 | B11: =VLOOKUP(VALUE(A11), 'DICIONÁRIO UF'!$A:$B, 2, FALSE) -> Rondônia | C11: 1111 | D11: =VLOOKUP(C11, 'DICIONÁRIO CNAES'!$A:$B, 2, FALSE) -> Cultivo de flores e plantas ornamentais | E11: 96.273407 | F11: 4813.6703
A12: 11 | B12: =VLOOKUP(VALUE(A12), 'DICIONÁRIO UF'!$A:$B, 2, FALSE) -> Rondônia | C12: 1112 | D12: =VLOOKUP(C12, 'DICIONÁRIO CNAES'!$A:$B, 2, FALSE) -> Cultivo de frutas cítricas | E12: 464.41331 | F12: 1219981.3
A13: 11 | B13: =VLOOKUP(VALUE(A13), 'DICIONÁRIO UF'!$A:$B, 2, FALSE) -> Rondônia | C13: 1113 | D13: =VLOOKUP(C13, 'DICIONÁRIO CNAES'!$A:$B, 2, FALSE) -> Cultivo de café | E13: 19669.696 | F13: 19802477
A14: 11 | B14: =VLOOKUP(VALUE(A14), 'DICIONÁRIO UF'!$A:$B, 2, FALSE) -> Rondônia | C14: 1114 | D14: =VLOOKUP(C14, 'DICIONÁRIO CNAES'!$A:$B, 2, FALSE) -> Cultivo de cacau | E14: 1308.3577 | F14: 1745646.5
A15: 11 | B15: =VLOOKUP(VALUE(A15), 'DICIONÁRIO UF'!$A:$B, 2, FALSE) -> Rondônia | C15: 1116 | D15: =VLOOKUP(C15, 'DICIONÁRIO CNAES'!$A:$B, 2, FALSE) -> Cultivo de banana | E15: 1339.8327 | F15: 1403484.8
A16: 11 | B16: =VLOOKUP(VALUE(A16), 'DICIONÁRIO UF'!$A:$B, 2, FALSE) -> Rondônia | C16: 1117 | D16: =VLOOKUP(C16, 'DICIONÁRIO CNAES'!$A:$B, 2, FALSE) -> Cultivo de outras plantas e frutas de lavoura permanente não especificadas anteriormente | E16: 2728.098 | F16: 2973239.7
A17: 11 | B17: =VLOOKUP(VALUE(A17), 'DICIONÁRIO UF'!$A:$B, 2, FALSE) -> Rondônia | C17: 1119 | D17: =VLOOKUP(C17, 'DICIONÁRIO CNAES'!$A:$B, 2, FALSE) -> Lavoura não especificada | E17: 1809.245 | F17: 3228301.5
A18: 11 | B18: =VLOOKUP(VALUE(A18), 'DICIONÁRIO UF'!$A:$B, 2, FALSE) -> Rondônia | C18: 1201 | D18: =VLOOKUP(C18, 'DICIONÁRIO CNAES'!$A:$B, 2, FALSE) -> Criação de bovinos | E18: 90907.8 | F18: 1.6524017e+08
A19: 11 | B19: =VLOOKUP(VALUE(A19), 'DICIONÁRIO UF'!$A:$B, 2, FALSE) -> Rondônia | C19: 1202 | D19: =VLOOKUP(C19, 'DICIONÁRIO CNAES'!$A:$B, 2, FALSE) -> Criação de outros animais de grande porte não especificados anteriormente | E19: 178.32158 | F19: 196153.74
... A4705: 53 | B4705: =VLOOKUP(VALUE(A4705), 'DICIONÁRIO UF'!$A:$B, 2, FALSE) -> Distrito Federal | C4705: 99000 | D4705: =VLOOKUP(C4705, 'DICIONÁRIO CNAES'!$A:$B, 2, FALSE) -> Organismos internacionais e outras instituições extraterritoriais | E4705: 1678.063 | F4705: 28453505

Sheet DICIONÁRIO CNAES
A1: Classe | B1: Denominação
A2: 1101 | B2: Cultivo de arroz
A3: 1102 | B3: Cultivo de milho
A4: 1103 | B4: Cultivo de outros cereais
A5: 1104 | B5: Cultivo de algodão
A6: 1105 | B6: Cultivo de cana-de-açúcar
A7: 1106 | B7: Cultivo de fumo
A8: 1107 | B8: Cultivo de soja
A9: 1108 | B9: Cultivo de mandioca
A10: 1109 | B10: Cultivo de outras lavouras temporárias não especificadas anteriormente
A11: 1110 | B11: Horticultura
A12: 1111 | B12: Cultivo de flores e plantas ornamentais
A13: 1112 | B13: Cultivo de frutas cítricas
... A33: 1999 | B33: Agropecuária
B34: PRODUÇÃO FLORESTAL
A35: 2000 | B35: Produção florestal
B36: PESCA E AQÜICULTURA
A37: 3001 | B37: Pesca
A38: 3002 | B38: Aqüicultura
B39: INDÚSTRIAS EXTRATIVAS
B40: EXTRAÇÃO DE CARVÃO MINERAL
A41: 5000 | B41: Extração de carvão mineral
B42: EXTRAÇÃO DE PETRÓLEO E GÁS NATURAL
A43: 6000 | B43: Extração de petróleo e gás natural
B44: EXTRAÇÃO DE MINERAIS METÁLICOS
A45: 7001 | B45: Extração de minérios de metais preciosos
A46: 7002 | B46: Extração de minerais metálicos não especificados anteriormente
B47: EXTRAÇÃO DE MINERAIS NÃO-METÁLICOS
A48: 8001 | B48: Extração de pedras, areia e argila
A49: 8002 | B49: Extração de gemas (pedras preciosas e semi-preciosas)
A50: 8009 | B50: Extração de minerais não metálicos não especificados anteriormente
B51: ATIVIDADES DE APOIO À EXTRAÇÃO DE MINERAIS
A52: 9000 | B52: Atividades de apoio à extração de minerais
B53: INDÚSTRIAS DE TRANSFORMAÇÃO
B54: FABRICAÇÃO DE PRODUTOS ALIMENTÍCIOS
A55: 10010 | B55: Abate e fabricação de produtos de carne e pescado
A56: 10021 | B56: Fabricação de conservas de frutas, legumes e outros vegetais
A57: 10022 | B57: Fabricação de óleos vegetais e gorduras vegetais e animais
A58: 10030 | B58: Laticínios
A59: 10091 | B59: Moagem, fabricação de produtos amiláceos e de alimentos para animais
A60: 10092 | B60: Fabricação e refino do açúcar
A61: 10093 | B61: Torrefação e moagem de café
A62: 10099 | B62: Fabricação de outros produtos alimentícios
B63: FABRICAÇÃO DE BEBIDAS
A64: 11000 | B64: Fabricação de bebidas
B65: FABRICAÇÃO DE PRODUTOS DO FUMO
A66: 12000 | B66: Processamento industrial e fabricação de produtos do fumo
B67: FABRICAÇÃO DE PRODUTOS TÊXTEIS
A68: 13001 | B68: Preparação de fibras, fiação e tecelagem
A69: 13002 | B69: Fabricação de artefatos têxteis, exceto vestuário
B70: CONFECÇÃO DE ARTIGOS DO VESTUÁRIO E ACESSÓRIOS
A71: 14001 | B71: Confecção de artigos do vestuário e acessórios, exceto sob medida
A72: 14002 | B72: Confecção, sob medida, de artigos do vestuário
B73: PREPARAÇÃO DE COUROS E FABRICAÇÃO DE ARTEFATOS DE COURO, ARTIGOS DE VIAGEM E CALÇADOS
A74: 15011 | B74: Curtimento e outras preparações de couro
A75: 15012 | B75: Fabricação de artigos de viagem e de artefatos diversos de couro
A76: 15020 | B76: Fabricação de calçados e partes para calçados, de qualquer material
B77: FABRICAÇÃO DE PRODUTOS DE MADEIRA
A78: 16001 | B78: Serrarias
A79: 16002 | B79: Fabricação de produtos de madeira, cortiça e material trançado, exceto móveis
B80: FABRICAÇÃO DE CELULOSE, PAPEL E PRODUTOS DE PAPEL
A81: 17001 | B81: Fabricação de celulose, papel, cartolina e papel-cartão
A82: 17002 | B82: Fabricação de embalagens e de produtos diversos de papel, cartolina, papel-cartão e papelão ondulado
B83: IMPRESSÃO E REPRODUÇÃO DE GRAVAÇÕES
A84: 18000 | B84: Impressão e reprodução de gravações
B85: FABRICAÇÃO DE COQUE; PRODUTOS DERIVADOS DE PETRÓLEO E DE BIOCOMBUSTÍVEIS
A86: 19010 | B86: Coquerias
A87: 19020 | B87: Fabricação de produtos derivados do petróleo
A88: 19030 | B88: Produção de biocombustíveis
B89: FABRICAÇÃO DE PRODUTOS QUÍMICOS
A90: 20010 | B90: Fabricação de tintas, vernizes, esmaltes, lacas e produtos afins
A91: 20020 | B91: Fabricação de sabões, detergentes, produtos de limpeza, cosméticos, produtos de perfumaria e de higiene pessoal
A92: 20090 | B92: Fabricação de outros produtos químicos não especificados anteriormente
B93: FABRICAÇÃO DE PRODUTOS FARMOQUÍMICOS E FARMACÊUTICOS
A94: 21000 | B94: Fabricação de produtos farmoquimicos e farmacêuticos
B95: FABRICAÇÃO DE PRODUTOS DE BORRACHA E DE MATERIAL PLÁSTICO
A96: 22010 | B96: Fabricação de produtos de borracha
A97: 22020 | B97: Fabricação de produtos de material plástico
B98: FABRICAÇÃO DE PRODUTOS DE MINERAIS NÃO-METÁLICOS
A99: 23010 | B99: Fabricação de vidro e produtos de vidro
A100: 23091 | B100: Fabricação de produtos cerâmicos
A101: 23099 | B101: Fabricação de outros produtos de minerais não-metálicos não especificados anteriormente
B102: METALURGIA
A103: 24001 | B103: Fabricação de produtos siderúrgicos
A104: 24002 | B104: Metalurgia dos metais não-ferrosos
A105: 24003 | B105: Fundição
B106: FABRICAÇÃO DE PRODUTOS DE METAL, EXCETO MÁQUINAS E EQUIPAMENTOS
A107: 25001 | B107: Fabricação de produtos de metal, exceto máquinas e equipamentos
A108: 25002 | B108: Forjaria, estamparia, metalurgia do pó e serviços de tratamento de metais
B109: FABRICAÇÃO DE EQUIPAMENTOS DE INFORMÁTICA, PRODUTOS ELETRÔNICOS E ÓPTICOS
A110: 26010 | B110: Fabricação de componentes eletrônicos
A111: 26020 | B111: Fabricação de equipamentos de informática e periféricos
A112: 26030 | B112: Fabricação de equipamentos de comunicação e de aparelhos de recepção, reprodução, gravação e amplificação de áudio e vídeo
A113: 26041 | B113: Fabricação de aparelhos e instrumentos de medida, teste e controle; cronômetros e relógios e de aparelhos eletromédicos e eletroterapêuticos
A114: 26042 | B114: Fabricação de equipamentos e instrumentos ópticos, fotográficos e cinematográficos e de mídias virgens, magnéticas e ópticas
B115: FABRICAÇÃO DE MÁQUINAS, APARELHOS E MATERIAIS ELÉTRICOS
A116: 27010 | B116: Fabricação de eletrodomesticos
A117: 27090 | B117: Fabricação de máquinas, aparelhos e materiais elétricos diversos, exceto eletrodomesticos
B118: FABRICAÇÃO DE MÁQUINAS E EQUIPAMENTOS
A119: 28000 | B119: Fabricação de máquinas e equipamentos
...

Sheet DICIONÁRIO UF
A1: Tipo | B1: Descrição
A2: 11 | B2: Rondônia
A3: 12 | B3: Acre
A4: 13 | B4: Amazonas
A5: 14 | B5: Roraima
A6: 15 | B6: Pará
A7: 16 | B7: Amapá
A8: 17 | B8: Tocantins
A9: 21 | B9: Maranhão
A10: 22 | B10: Piauí
A11: 23 | B11: Ceará
A12: 24 | B12: Rio Grande do Norte
A13: 25 | B13: Paraíba
... A28: 53 | B28: Distrito Federal
